vox_serve/__init__.py
vox_serve/flashinfer_utils.py
vox_serve/launch.py
vox_serve/requests.py
vox_serve/sampling.py
vox_serve/utils.py
vox_serve/encoder/glm.py
vox_serve/encoder/step_audio_2.py
vox_serve/encoder/zonos.py
vox_serve/model/__init__.py
vox_serve/model/base.py
vox_serve/model/csm.py
vox_serve/model/glm_voice.py
vox_serve/model/orpheus.py
vox_serve/model/step_audio_2.py
vox_serve/model/zonos.py
vox_serve/scheduler/__init__.py
vox_serve/scheduler/base.py
vox_serve/scheduler/offline.py
vox_serve/scheduler/online.py
vox_serve/tokenizer/base.py
vox_serve/tokenizer/dac.py
vox_serve/tokenizer/glm.py
vox_serve/tokenizer/mimi.py
vox_serve/tokenizer/s3.py
vox_serve/tokenizer/snac.py
vox_serve/tokenizer/step_audio_2.py
vox_serve/watermarker/silentcipher.py
vox_serve/worker/__init__.py
vox_serve/worker/base.py
vox_serve/worker/cuda_graph_worker.py
vox_serve-0.0.1.dist-info/licenses/LICENSE
vox_serve-0.0.1.dist-info/METADATA
vox_serve-0.0.1.dist-info/WHEEL
vox_serve-0.0.1.dist-info/entry_points.txt
vox_serve-0.0.1.dist-info/top_level.txt
vox_serve-0.0.1.dist-info/RECORD
