Metadata-Version: 2.4
Name: vox-serve
Version: 0.0.1
Summary: A serving system for speech language models.
Author: VoxServe Team
Maintainer: VoxServe Team
License:                                  Apache License
Project-URL: Homepage, https://github.com/vox-serve/vox-serve
Project-URL: Repository, https://github.com/vox-serve/vox-serve
Project-URL: Issues, https://github.com/vox-serve/vox-serve/issues
Project-URL: Documentation, https://github.com/vox-serve/vox-serve#readme
Keywords: speech,language-models,tts,speech-to-speech,inference,serving
Classifier: Development Status :: 3 - Alpha
Classifier: Intended Audience :: Developers
Classifier: Intended Audience :: Science/Research
Classifier: License :: OSI Approved :: Apache Software License
Classifier: Operating System :: OS Independent
Classifier: Programming Language :: Python :: 3
Classifier: Programming Language :: Python :: 3.12
Classifier: Topic :: Scientific/Engineering :: Artificial Intelligence
Classifier: Topic :: Software Development :: Libraries :: Python Modules
Classifier: Topic :: Multimedia :: Sound/Audio :: Speech
Requires-Python: >=3.12
License-File: LICENSE
Requires-Dist: diffusers==0.34.0
Requires-Dist: fastapi==0.116.1
Requires-Dist: flashinfer-python==0.2.11.post1
Requires-Dist: huggingface-hub==0.34.0
Requires-Dist: librosa==0.10.2.post1
Requires-Dist: numpy==1.26.4
Requires-Dist: safetensors==0.5.3
Requires-Dist: scipy==1.11.4
Requires-Dist: soundfile==0.12.1
Requires-Dist: torch==2.8.0
Requires-Dist: torchaudio==2.8.0
Requires-Dist: transformers==4.55.0
Requires-Dist: uvicorn==0.35.0
Requires-Dist: zmq==0.0.0
Requires-Dist: httptools==0.6.4
Requires-Dist: uvloop==0.21.0
Requires-Dist: phonemizer>=3.3.0
Requires-Dist: pydub>=0.25.1
Requires-Dist: python-multipart>=0.0.20
Requires-Dist: aiohttp>=3.12.15
Requires-Dist: onnxruntime>=1.22.1
Requires-Dist: onnx>=1.19.0
Requires-Dist: tiktoken>=0.11.0
Dynamic: license-file
